Metadata-Version: 2.1
Name: cuspy
Version: 0.1.3
Summary: Config Utils for Python
Home-page: 
Author: zbc
Author-email: zbc@mail.ustc.edu.cn
Classifier: Programming Language :: Python :: 3
Classifier: License :: OSI Approved :: MIT License
Classifier: Operating System :: OS Independent
Requires-Python: >=3.5
